bin/__init__.py
bin/dcg.py
bin/test_dotsCodeGenerator.py
dots/__init__.py
dots/parser.py
dots/template.py
dots/test_ddlParser.py
dots_code_generator-0.0.4.data/scripts/dcg.py
dots_code_generator-0.0.4.dist-info/LICENSE
dots_code_generator-0.0.4.dist-info/METADATA
dots_code_generator-0.0.4.dist-info/WHEEL
dots_code_generator-0.0.4.dist-info/top_level.txt
dots_code_generator-0.0.4.dist-info/RECORD
