Metadata-Version: 2.1
Name: dots-code-generator
Version: 0.0.4
Summary: DOTS code generator
Home-page: https://github.com/pnxs/dots-code-generator
Author: Thomas Schaetzlein
Author-email: pypi@thomas.pnxs.de
License: UNKNOWN
Platform: UNKNOWN
Classifier: Programming Language :: Python :: 3
Classifier: License :: OSI Approved :: GNU General Public License v3 (GPLv3)
Classifier: Operating System :: OS Independent
Requires-Python: >=3.6
Requires-Dist: simpleparse
Requires-Dist: jinja2
